gradio_labanmovementanalysis/__init__.py
gradio_labanmovementanalysis/agent_api.py
gradio_labanmovementanalysis/json_generator.py
gradio_labanmovementanalysis/labanmovementanalysis.py
gradio_labanmovementanalysis/notation_engine.py
gradio_labanmovementanalysis/pose_estimation.py
gradio_labanmovementanalysis/video_downloader.py
gradio_labanmovementanalysis/video_utils.py
gradio_labanmovementanalysis/visualizer.py
gradio_labanmovementanalysis-0.0.5.dist-info/METADATA
gradio_labanmovementanalysis-0.0.5.dist-info/WHEEL
gradio_labanmovementanalysis-0.0.5.dist-info/licenses/LICENSE
gradio_labanmovementanalysis-0.0.5.dist-info/RECORD
