Metadata-Version: 2.4
Name: gradio_labanmovementanalysis
Version: 0.0.5
Summary: A Gradio 5 component for video movement analysis using Laban Movement Analysis (LMA) with MCP support for AI agents
Author-email: Csaba Bolyós <bladeszasza@gmail.com>
License-Expression: Apache-2.0
License-File: LICENSE
Keywords: LMA,ai-agents,gradio-5,gradio-custom-component,laban-movement-analysis,mcp,movement-analysis,pose-estimation
Requires-Python: >=3.10
Requires-Dist: gradio[mcp]>=5.33.0
Requires-Dist: mcp>=1.9.0
Requires-Dist: mediapipe>=0.10.21
Requires-Dist: opencv-python>=4.8.0
Requires-Dist: tensorflow-hub>=0.12.0
Requires-Dist: tensorflow>=2.8.0
Requires-Dist: ultralytics>=8.0.0
Requires-Dist: yt-dlp>=2025.05.22
Provides-Extra: dev
Requires-Dist: build; extra == 'dev'
Requires-Dist: twine; extra == 'dev'
